{
  "abstract": "[No description]",
  "filename": "/vol/winshare/Public/ResearchData/HUM/LUCL-KlamerVICI/sunda_database_raw_git/lexirumah-data/datasets/abzatimelangas2010wordlist.tsv",
  "id": "abzatimelangas2010wordlist",
  "language": "atim1239",
  "name": "ABZ_Atimelang_AS_2010_word list",
  "sources": [
    {
      "date": "2010-07-17",
      "location": "Atengmelang",
      "recorders": [
        "Antoinette Schapper"
      ],
      "speakers": [
        {
          "date of birth": "1971-11-03",
          "name": "Semuel Mailet",
          "place of birth": "Atengmelang"
        }
      ]
    }
  ]
}